hardcore_restore/backup.py
hardcore_restore/cli.py
hardcore_restore/restore.py
hardcore_restore/statistics.py
hardcore_restore/utils.py
hardcore_restore-0.0.1.dist-info/METADATA
hardcore_restore-0.0.1.dist-info/WHEEL
hardcore_restore-0.0.1.dist-info/entry_points.txt
hardcore_restore-0.0.1.dist-info/RECORD
