Metadata-Version: 2.4
Name: hardcore-restore
Version: 0.0.1
Summary: Restore death in a minecraft hardcore world. Should work on all platforms with java edition, but wasn't tested.
Project-URL: Homepage, https://gitlab.com/leswell/hardcore-restore/-/blob/main/README.md
Project-URL: Repository, https://gitlab.com/leswell/hardcore-restore
Author-email: Simofi Levente <simofilevente+pypi@gmail.com>
Maintainer-email: Simofi Levente <simofilevente+pypi@gmail.com>
License-Expression: GPL-3.0-or-later
Classifier: Development Status :: 3 - Alpha
Classifier: Programming Language :: Python :: 3
Classifier: Typing :: Typed
Requires-Python: >=3.10
Requires-Dist: black
Requires-Dist: nbtlib
Requires-Dist: typer
